live_recorder/__init__.py
live_recorder/__main__.py
live_recorder/version.py
live_recorder/you_live/__init__.py
live_recorder/you_live/_base_recorder.py
live_recorder/you_live/_recorder.py
live_recorder/you_live/acfun_recorder.py
live_recorder/you_live/bili_recorder.py
live_recorder/you_live/douyu_recorder.py
live_recorder/you_live/flv_checker.py
live_recorder/you_live/kuaishou_recorder.py
live_recorder/you_live/live_thread/__init__.py
live_recorder/you_live/live_thread/download.py
live_recorder/you_live/live_thread/monitoring.py
live_recorder/you_live/resources/__init__.py
live_recorder/you_live/resources/crypto.py
you_live-1.1.5.dist-info/LICENSE.txt
you_live-1.1.5.dist-info/METADATA
you_live-1.1.5.dist-info/WHEEL
you_live-1.1.5.dist-info/entry_points.txt
you_live-1.1.5.dist-info/top_level.txt
you_live-1.1.5.dist-info/zip-safe
you_live-1.1.5.dist-info/RECORD
